{"textures":{"0":"modelengine:entity/vulture"},"elements":[{"from":[8.571428,4.913086,7.047361],"to":[8.571428,11.198801,16.19022],"rotation":{"angle":0.0,"axis":"y","origin":[12.714286,-0.22977161,7.047361]},"faces":{"east":{"uv":[4.0,0.0,8.0,2.75],"rotation":0,"texture":"#0","tintindex":0},"south":{"uv":[0.0,0.0,0.0,2.75],"rotation":0,"texture":"#0","tintindex":0},"north":{"uv":[0.0,0.0,0.0,2.75],"rotation":0,"texture":"#0","tintindex":0},"west":{"uv":[4.0,2.75,8.0,5.5],"rotation":0,"texture":"#0","tintindex":0},"up":{"uv":[0.0,4.0,0.0,0.0],"rotation":0,"texture":"#0","tintindex":0},"down":{"uv":[0.0,0.0,0.0,4.0],"rotation":0,"texture":"#0","tintindex":0}}},{"from":[8.142858,5.4845147,7.047361],"to":[8.714286,10.0559435,14.475933],"rotation":{"angle":0.0,"axis":"y","origin":[17.857143,-0.22977161,7.047361]},"faces":{"east":{"uv":[6.5,5.5,9.75,7.5],"rotation":0,"texture":"#0","tintindex":0},"south":{"uv":[0.75,13.0,1.0,15.0],"rotation":0,"texture":"#0","tintindex":0},"north":{"uv":[0.5,13.0,0.75,15.0],"rotation":0,"texture":"#0","tintindex":0},"west":{"uv":[0.0,7.5,3.25,9.5],"rotation":0,"texture":"#0","tintindex":0},"up":{"uv":[3.75,15.75,3.5,12.5],"rotation":0,"texture":"#0","tintindex":0},"down":{"uv":[4.0,12.5,3.75,15.75],"rotation":0,"texture":"#0","tintindex":0}}}],"display":{"head":{"translation":[0.0,-6.4,0.0],"scale":[4.0,4.0,4.0]}}}